{
    "regionCode": "09186",
    "timestamp": {
        "start": "1656821700",
        "end": "1656822600"
    },
    "autarky": "31.17534211749286",
    "secondaryInFeed": "11530.90258154248",
    "consumptions": {
        "list": [
            {
                "name": "domestic",
                "unit": "kWh",
                "usage": "1748.2038129632447",
                "numberOfInstallations": "59858",
                "timestamp": "1656821700"
            },
            {
                "name": "public",
                "unit": "kWh",
                "usage": "192.20286032449087",
                "numberOfInstallations": "1156",
                "timestamp": "1656821700"
            },
            {
                "name": "industrial",
                "unit": "kWh",
                "usage": "14813.621514149483",
                "numberOfInstallations": "8381",
                "timestamp": "1656821700"
            }
        ],
        "total": "16754.02818743722"
    },
    "feedIn": {
        "list": [
            {
                "name": "bio",
                "unit": "kWh",
                "usage": "2175.3338476325525",
                "numberOfInstallations": "26",
                "installedCapacity": "13614.6",
                "timestamp": "1656821700"
            },
            {
                "name": "solar",
                "unit": "kWh",
                "usage": "1902.8212318666747",
                "numberOfInstallations": "8161",
                "installedCapacity": "167443.74601612898",
                "timestamp": "1656821700"
            },
            {
                "name": "water",
                "unit": "kWh",
                "usage": "168.8006113619924",
                "numberOfInstallations": "32",
                "installedCapacity": "2369",
                "timestamp": "1656821700"
            },
            {
                "name": "others",
                "unit": "kWh",
                "usage": "503.29396866219065",
                "numberOfInstallations": "79",
                "installedCapacity": "15720.85",
                "timestamp": "1656821700"
            },
            {
                "name": "wind",
                "unit": "kWh",
                "usage": "472.87594637133105",
                "numberOfInstallations": "13",
                "installedCapacity": "44752.8",
                "timestamp": "1656821700"
            }
        ],
        "total": "5223.125605894741"
    },
    "energyMix": "28.480065283287235",
    "dailyCo2Savings": "18334.471269273985"
}