{
    "regionCode": "09188113",
    "timestamp": {
        "start": "1667512800",
        "end": "1667513700"
    },
    "autarky": "100.0",
    "secondaryInFeed": "0.0",
    "consumptions": {
        "list": [
            {
                "name": "domestic",
                "unit": "kWh",
                "usage": "480.3095931870568",
                "numberOfInstallations": "4144",
                "timestamp": "1667512800"
            },
            {
                "name": "public",
                "unit": "kWh",
                "usage": "48.36390042802257",
                "numberOfInstallations": "80",
                "timestamp": "1667512800"
            },
            {
                "name": "industrial",
                "unit": "kWh",
                "usage": "169.4864583040711",
                "numberOfInstallations": "584",
                "timestamp": "1667512800"
            }
        ],
        "total": "698.1599519191504"
    },
    "feedIn": {
        "list": [
            {
                "name": "bio",
                "unit": "kWh",
                "usage": "0",
                "numberOfInstallations": "1",
                "installedCapacity": "8",
                "timestamp": "1667512800"
            },
            {
                "name": "solar",
                "unit": "kWh",
                "usage": "0",
                "numberOfInstallations": "371",
                "installedCapacity": "4080.1240000000003",
                "timestamp": "1667512800"
            },
            {
                "name": "water",
                "unit": "kWh",
                "usage": "1.6747587054666",
                "numberOfInstallations": "3",
                "installedCapacity": "33.6",
                "timestamp": "1667512800"
            },
            {
                "name": "others",
                "unit": "kWh",
                "usage": "22.127786860854457",
                "numberOfInstallations": "13",
                "installedCapacity": "130.97",
                "timestamp": "1667512800"
            },
            {
                "name": "wind",
                "unit": "kWh",
                "usage": "1065.629271833743",
                "numberOfInstallations": "5",
                "installedCapacity": "12040",
                "timestamp": "1667512800"
            }
        ],
        "total": "1089.431817400064"
    },
    "energyMix": "100.0",
    "dailyCo2Savings": "25606.66413820371"
}