{
    "regionCode": "09188113",
    "timestamp": {
        "start": "1653801300",
        "end": "1653802200"
    },
    "autarky": "68.83299121843662",
    "secondaryInFeed": "130.11646626131818",
    "consumptions": {
        "list": [
            {
                "name": "domestic",
                "unit": "kWh",
                "usage": "257.81270041239486",
                "numberOfInstallations": "4129",
                "timestamp": "1653801300"
            },
            {
                "name": "public",
                "unit": "kWh",
                "usage": "13.191133814381843",
                "numberOfInstallations": "79",
                "timestamp": "1653801300"
            },
            {
                "name": "industrial",
                "unit": "kWh",
                "usage": "146.47757110554255",
                "numberOfInstallations": "584",
                "timestamp": "1653801300"
            }
        ],
        "total": "417.48140533231924"
    },
    "feedIn": {
        "list": [
            {
                "name": "bio",
                "unit": "kWh",
                "usage": "0",
                "numberOfInstallations": "1",
                "installedCapacity": "8",
                "timestamp": "1653801300"
            },
            {
                "name": "solar",
                "unit": "kWh",
                "usage": "100.13186344234899",
                "numberOfInstallations": "344",
                "installedCapacity": "3751.0690000000004",
                "timestamp": "1653801300"
            },
            {
                "name": "water",
                "unit": "kWh",
                "usage": "2.015936678679",
                "numberOfInstallations": "3",
                "installedCapacity": "33.6",
                "timestamp": "1653801300"
            },
            {
                "name": "others",
                "unit": "kWh",
                "usage": "13.430506290808855",
                "numberOfInstallations": "13",
                "installedCapacity": "130.97",
                "timestamp": "1653801300"
            },
            {
                "name": "wind",
                "unit": "kWh",
                "usage": "171.7866326591642",
                "numberOfInstallations": "5",
                "installedCapacity": "12040",
                "timestamp": "1653801300"
            }
        ],
        "total": "287.36493907100106"
    },
    "energyMix": "68.83299121843662"
}