{
    "regionCode": "09188113",
    "timestamp": {
        "start": "1652861700",
        "end": "1652862600"
    },
    "autarky": "97.02576988466203",
    "secondaryInFeed": "24.975591059504268",
    "consumptions": {
        "list": [
            {
                "name": "domestic",
                "unit": "kWh",
                "usage": "449.21881479767796",
                "numberOfInstallations": "4132",
                "timestamp": "1652861700"
            },
            {
                "name": "public",
                "unit": "kWh",
                "usage": "45.48914918161348",
                "numberOfInstallations": "79",
                "timestamp": "1652861700"
            },
            {
                "name": "industrial",
                "unit": "kWh",
                "usage": "345.0250119833329",
                "numberOfInstallations": "586",
                "timestamp": "1652861700"
            }
        ],
        "total": "839.7329759626243"
    },
    "feedIn": {
        "list": [
            {
                "name": "bio",
                "unit": "kWh",
                "usage": "0",
                "numberOfInstallations": "1",
                "installedCapacity": "8",
                "timestamp": "1652861700"
            },
            {
                "name": "solar",
                "unit": "kWh",
                "usage": "337.97860745194583",
                "numberOfInstallations": "344",
                "installedCapacity": "3744.099",
                "timestamp": "1652861700"
            },
            {
                "name": "water",
                "unit": "kWh",
                "usage": "2.015936678679",
                "numberOfInstallations": "3",
                "installedCapacity": "33.6",
                "timestamp": "1652861700"
            },
            {
                "name": "others",
                "unit": "kWh",
                "usage": "13.502073882746716",
                "numberOfInstallations": "13",
                "installedCapacity": "130.97",
                "timestamp": "1652861700"
            },
            {
                "name": "wind",
                "unit": "kWh",
                "usage": "461.26076688974854",
                "numberOfInstallations": "5",
                "installedCapacity": "12040",
                "timestamp": "1652861700"
            }
        ],
        "total": "814.75738490312"
    },
    "energyMix": "97.0257301895038"
}