{
    "regionCode": "09186",
    "timestamp": {
        "start": "1635243300",
        "end": "1635244200"
    },
    "autarky": "56.079865573767684",
    "secondaryInFeed": "11456.365708196774",
    "consumptions": {
        "list": [
            {
                "name": "domestic",
                "unit": "kWh",
                "usage": "7070.917428207802",
                "numberOfInstallations": "59539",
                "timestamp": "1635243300"
            },
            {
                "name": "public",
                "unit": "kWh",
                "usage": "633.1013030710968",
                "numberOfInstallations": "1105",
                "timestamp": "1635243300"
            },
            {
                "name": "industrial",
                "unit": "kWh",
                "usage": "18380.522807269295",
                "numberOfInstallations": "8368",
                "timestamp": "1635243300"
            }
        ],
        "total": "26084.541538548194"
    },
    "feedIn": {
        "list": [
            {
                "name": "bio",
                "unit": "kWh",
                "usage": "2100.875293523536",
                "numberOfInstallations": "26",
                "installedCapacity": "13696.8",
                "timestamp": "1635243300"
            },
            {
                "name": "solar",
                "unit": "kWh",
                "usage": "11167.195617804658",
                "numberOfInstallations": "7696",
                "installedCapacity": "176665.718016129",
                "timestamp": "1635243300"
            },
            {
                "name": "water",
                "unit": "kWh",
                "usage": "194.18489426689598",
                "numberOfInstallations": "32",
                "installedCapacity": "2354",
                "timestamp": "1635243300"
            },
            {
                "name": "others",
                "unit": "kWh",
                "usage": "746.3073655995236",
                "numberOfInstallations": "78",
                "installedCapacity": "15717.55",
                "timestamp": "1635243300"
            },
            {
                "name": "wind",
                "unit": "kWh",
                "usage": "419.61265915680485",
                "numberOfInstallations": "13",
                "installedCapacity": "44752.8",
                "timestamp": "1635243300"
            }
        ],
        "total": "14628.17583035142"
    },
    "energyMix": "53.63118538877736"
}