{
    "regionCode": "09188113",
    "timestamp": {
        "start": "1661526900",
        "end": "1661527800"
    },
    "autarky": "89.06642217742952",
    "secondaryInFeed": "74.28814994297466",
    "consumptions": {
        "list": [
            {
                "name": "domestic",
                "unit": "kWh",
                "usage": "359.3445879353185",
                "numberOfInstallations": "4140",
                "timestamp": "1661526900"
            },
            {
                "name": "public",
                "unit": "kWh",
                "usage": "55.619033891729295",
                "numberOfInstallations": "80",
                "timestamp": "1661526900"
            },
            {
                "name": "industrial",
                "unit": "kWh",
                "usage": "264.4859705069417",
                "numberOfInstallations": "583",
                "timestamp": "1661526900"
            }
        ],
        "total": "679.4495923339895"
    },
    "feedIn": {
        "list": [
            {
                "name": "bio",
                "unit": "kWh",
                "usage": "0",
                "numberOfInstallations": "1",
                "installedCapacity": "8",
                "timestamp": "1661526900"
            },
            {
                "name": "solar",
                "unit": "kWh",
                "usage": "274.76256917341254",
                "numberOfInstallations": "366",
                "installedCapacity": "4027.134",
                "timestamp": "1661526900"
            },
            {
                "name": "water",
                "unit": "kWh",
                "usage": "1.3670704353552",
                "numberOfInstallations": "3",
                "installedCapacity": "33.6",
                "timestamp": "1661526900"
            },
            {
                "name": "others",
                "unit": "kWh",
                "usage": "9.89450278224702",
                "numberOfInstallations": "12",
                "installedCapacity": "115.97",
                "timestamp": "1661526900"
            },
            {
                "name": "wind",
                "unit": "kWh",
                "usage": "319.13730000000015",
                "numberOfInstallations": "5",
                "installedCapacity": "12040",
                "timestamp": "1661526900"
            }
        ],
        "total": "605.1614423910148"
    },
    "energyMix": "89.06460698267888",
    "dailyCo2Savings": "11114.43632288285"
}