{
    "regionCode": "09186",
    "timestamp": {
        "start": "1652707800",
        "end": "1652708700"
    },
    "autarky": "62.68129823978751",
    "secondaryInFeed": "9582.76254277403",
    "consumptions": {
        "list": [
            {
                "name": "domestic",
                "unit": "kWh",
                "usage": "4369.002834965631",
                "numberOfInstallations": "59748",
                "timestamp": "1652707800"
            },
            {
                "name": "public",
                "unit": "kWh",
                "usage": "443.0813441119074",
                "numberOfInstallations": "1151",
                "timestamp": "1652707800"
            },
            {
                "name": "industrial",
                "unit": "kWh",
                "usage": "20866.0934926622",
                "numberOfInstallations": "8386",
                "timestamp": "1652707800"
            }
        ],
        "total": "25678.177671739737"
    },
    "feedIn": {
        "list": [
            {
                "name": "bio",
                "unit": "kWh",
                "usage": "2160.2108476325525",
                "numberOfInstallations": "27",
                "installedCapacity": "13704.6",
                "timestamp": "1652707800"
            },
            {
                "name": "solar",
                "unit": "kWh",
                "usage": "12375.469947500713",
                "numberOfInstallations": "8009",
                "installedCapacity": "165448.37101612898",
                "timestamp": "1652707800"
            },
            {
                "name": "water",
                "unit": "kWh",
                "usage": "226.28777325901828",
                "numberOfInstallations": "32",
                "installedCapacity": "2369",
                "timestamp": "1652707800"
            },
            {
                "name": "others",
                "unit": "kWh",
                "usage": "513.0208315761354",
                "numberOfInstallations": "79",
                "installedCapacity": "15747.25",
                "timestamp": "1652707800"
            },
            {
                "name": "wind",
                "unit": "kWh",
                "usage": "820.4257289972886",
                "numberOfInstallations": "13",
                "installedCapacity": "44752.8",
                "timestamp": "1652707800"
            }
        ],
        "total": "16095.415128965707"
    },
    "energyMix": "60.9769519026748"
}