{
    "regionCode": "09186",
    "timestamp": {
        "start": "1669388400",
        "end": "1669389300"
    },
    "autarky": "17.915150436058486",
    "secondaryInFeed": "23311.675776005213",
    "consumptions": {
        "list": [
            {
                "name": "domestic",
                "unit": "kWh",
                "usage": "6142.972874055792",
                "numberOfInstallations": "61583",
                "timestamp": "1669388400"
            },
            {
                "name": "public",
                "unit": "kWh",
                "usage": "620.4459934047616",
                "numberOfInstallations": "1179",
                "timestamp": "1669388400"
            },
            {
                "name": "industrial",
                "unit": "kWh",
                "usage": "21636.067639298715",
                "numberOfInstallations": "10476",
                "timestamp": "1669388400"
            }
        ],
        "total": "28399.48650675927"
    },
    "feedIn": {
        "list": [
            {
                "name": "bio",
                "unit": "kWh",
                "usage": "2696.8338465796915",
                "numberOfInstallations": "29",
                "installedCapacity": "13614.6",
                "timestamp": "1669388400"
            },
            {
                "name": "solar",
                "unit": "kWh",
                "usage": "321.60758164269953",
                "numberOfInstallations": "9123",
                "installedCapacity": "190566.54112999997",
                "timestamp": "1669388400"
            },
            {
                "name": "water",
                "unit": "kWh",
                "usage": "264.48234117366616",
                "numberOfInstallations": "33",
                "installedCapacity": "2708.504",
                "timestamp": "1669388400"
            },
            {
                "name": "others",
                "unit": "kWh",
                "usage": "833.0560623608285",
                "numberOfInstallations": "88",
                "installedCapacity": "18424.03",
                "timestamp": "1669388400"
            },
            {
                "name": "wind",
                "unit": "kWh",
                "usage": "971.8308989971681",
                "numberOfInstallations": "13",
                "installedCapacity": "44752.8",
                "timestamp": "1669388400"
            }
        ],
        "total": "5087.810730754054"
    },
    "energyMix": "15.423965728880956",
    "dailyCo2Savings": "102610.74068094708"
}