{
    "regionCode": "09186",
    "timestamp": {
        "start": "1645319700",
        "end": "1645320600"
    },
    "autarky": "30.624831672379234",
    "secondaryInFeed": "13815.721092254733",
    "consumptions": {
        "list": [
            {
                "name": "domestic",
                "unit": "kWh",
                "usage": "4494.191895807164",
                "numberOfInstallations": "59586",
                "timestamp": "1645319700"
            },
            {
                "name": "public",
                "unit": "kWh",
                "usage": "570.4135718780408",
                "numberOfInstallations": "1160",
                "timestamp": "1645319700"
            },
            {
                "name": "industrial",
                "unit": "kWh",
                "usage": "14849.899138646964",
                "numberOfInstallations": "8386",
                "timestamp": "1645319700"
            }
        ],
        "total": "19914.504606332168"
    },
    "feedIn": {
        "list": [
            {
                "name": "bio",
                "unit": "kWh",
                "usage": "2194.481159276351",
                "numberOfInstallations": "27",
                "installedCapacity": "13704.6",
                "timestamp": "1645319700"
            },
            {
                "name": "solar",
                "unit": "kWh",
                "usage": "0",
                "numberOfInstallations": "7885",
                "installedCapacity": "178884.21001612899",
                "timestamp": "1645319700"
            },
            {
                "name": "water",
                "unit": "kWh",
                "usage": "275.5460867226739",
                "numberOfInstallations": "32",
                "installedCapacity": "2369",
                "timestamp": "1645319700"
            },
            {
                "name": "others",
                "unit": "kWh",
                "usage": "664.1717728258545",
                "numberOfInstallations": "78",
                "installedCapacity": "15717.55",
                "timestamp": "1645319700"
            },
            {
                "name": "wind",
                "unit": "kWh",
                "usage": "2964.5844952525563",
                "numberOfInstallations": "13",
                "installedCapacity": "44752.8",
                "timestamp": "1645319700"
            }
        ],
        "total": "6098.783514077435"
    },
    "energyMix": "27.999653449185065"
}