{
    "regionCode": "09188113",
    "timestamp": {
        "start": "1672722000",
        "end": "1672722900"
    },
    "autarky": "45.450501468767406",
    "secondaryInFeed": "323.9747586322293",
    "consumptions": {
        "list": [
            {
                "name": "domestic",
                "unit": "kWh",
                "usage": "389.0953467127363",
                "numberOfInstallations": "4144",
                "timestamp": "1672722000"
            },
            {
                "name": "public",
                "unit": "kWh",
                "usage": "31.039440118053708",
                "numberOfInstallations": "69",
                "timestamp": "1672722000"
            },
            {
                "name": "industrial",
                "unit": "kWh",
                "usage": "173.7749050185969",
                "numberOfInstallations": "585",
                "timestamp": "1672722000"
            }
        ],
        "total": "593.9096918493868"
    },
    "feedIn": {
        "list": [
            {
                "name": "bio",
                "unit": "kWh",
                "usage": "0",
                "numberOfInstallations": "1",
                "installedCapacity": "8",
                "timestamp": "1672722000"
            },
            {
                "name": "solar",
                "unit": "kWh",
                "usage": "0",
                "numberOfInstallations": "378",
                "installedCapacity": "4148.669",
                "timestamp": "1672722000"
            },
            {
                "name": "water",
                "unit": "kWh",
                "usage": "1.6524769451681998",
                "numberOfInstallations": "3",
                "installedCapacity": "33.6",
                "timestamp": "1672722000"
            },
            {
                "name": "others",
                "unit": "kWh",
                "usage": "23.87929458706375",
                "numberOfInstallations": "12",
                "installedCapacity": "127.77",
                "timestamp": "1672722000"
            },
            {
                "name": "wind",
                "unit": "kWh",
                "usage": "244.40316168492558",
                "numberOfInstallations": "5",
                "installedCapacity": "12040",
                "timestamp": "1672722000"
            }
        ],
        "total": "269.93493321715755"
    },
    "energyMix": "45.45033309300022",
    "dailyCo2Savings": "3998.424334155839"
}