{
    "regionCode": "09188113",
    "timestamp": {
        "start": "1651335300",
        "end": "1651336200"
    },
    "autarky": "26.939806093278577",
    "secondaryInFeed": "656.1129871952353",
    "consumptions": {
        "list": [
            {
                "name": "domestic",
                "unit": "kWh",
                "usage": "665.8865183256754",
                "numberOfInstallations": "4130",
                "timestamp": "1651335300"
            },
            {
                "name": "public",
                "unit": "kWh",
                "usage": "53.87581721129074",
                "numberOfInstallations": "79",
                "timestamp": "1651335300"
            },
            {
                "name": "industrial",
                "unit": "kWh",
                "usage": "178.28207429983004",
                "numberOfInstallations": "586",
                "timestamp": "1651335300"
            }
        ],
        "total": "898.0444098367961"
    },
    "feedIn": {
        "list": [
            {
                "name": "bio",
                "unit": "kWh",
                "usage": "0",
                "numberOfInstallations": "1",
                "installedCapacity": "8",
                "timestamp": "1651335300"
            },
            {
                "name": "solar",
                "unit": "kWh",
                "usage": "33.25690347824251",
                "numberOfInstallations": "341",
                "installedCapacity": "3701.928999999999",
                "timestamp": "1651335300"
            },
            {
                "name": "water",
                "unit": "kWh",
                "usage": "2.4650617150428",
                "numberOfInstallations": "3",
                "installedCapacity": "33.6",
                "timestamp": "1651335300"
            },
            {
                "name": "others",
                "unit": "kWh",
                "usage": "17.431937805418375",
                "numberOfInstallations": "13",
                "installedCapacity": "130.97",
                "timestamp": "1651335300"
            },
            {
                "name": "wind",
                "unit": "kWh",
                "usage": "188.77751964285716",
                "numberOfInstallations": "5",
                "installedCapacity": "12040",
                "timestamp": "1651335300"
            }
        ],
        "total": "241.93142264156086"
    },
    "energyMix": "26.9237341338351"
}