{
    "regionCode": "09375",
    "timestamp": {
        "start": "1672056900",
        "end": "1672057800"
    },
    "autarky": "58.205099102303926",
    "secondaryInFeed": "8992.661381283768",
    "consumptions": {
        "list": [
            {
                "name": "domestic",
                "unit": "kWh",
                "usage": "14785.627119367346",
                "numberOfInstallations": "98160",
                "timestamp": "1672056900"
            },
            {
                "name": "public",
                "unit": "kWh",
                "usage": "447.2455906251138",
                "numberOfInstallations": "1723",
                "timestamp": "1672056900"
            },
            {
                "name": "industrial",
                "unit": "kWh",
                "usage": "6283.29598076638",
                "numberOfInstallations": "12530",
                "timestamp": "1672056900"
            }
        ],
        "total": "21516.168690758837"
    },
    "feedIn": {
        "list": [
            {
                "name": "bio",
                "unit": "kWh",
                "usage": "895.1366521042999",
                "numberOfInstallations": "19",
                "installedCapacity": "7633.9",
                "timestamp": "1672056900"
            },
            {
                "name": "solar",
                "unit": "kWh",
                "usage": "989.173719345036",
                "numberOfInstallations": "15707",
                "installedCapacity": "407390.43500000006",
                "timestamp": "1672056900"
            },
            {
                "name": "water",
                "unit": "kWh",
                "usage": "6220.09065587262",
                "numberOfInstallations": "80",
                "installedCapacity": "31827.7",
                "timestamp": "1672056900"
            },
            {
                "name": "others",
                "unit": "kWh",
                "usage": "253.55022385649048",
                "numberOfInstallations": "120",
                "installedCapacity": "6622.915",
                "timestamp": "1672056900"
            },
            {
                "name": "wind",
                "unit": "kWh",
                "usage": "4165.556058296622",
                "numberOfInstallations": "21",
                "installedCapacity": "32815.1",
                "timestamp": "1672056900"
            }
        ],
        "total": "12523.50730947507"
    },
    "energyMix": "58.014567138413874",
    "dailyCo2Savings": "233138.14364069988"
}