{
    "regionCode": "09375",
    "timestamp": {
        "start": "1646702100",
        "end": "1646703000"
    },
    "autarky": "56.09967428856242",
    "secondaryInFeed": "5631.759208584135",
    "consumptions": {
        "list": [
            {
                "name": "domestic",
                "unit": "kWh",
                "usage": "7432.054189275831",
                "numberOfInstallations": "97631",
                "timestamp": "1646702100"
            },
            {
                "name": "public",
                "unit": "kWh",
                "usage": "906.0005410888931",
                "numberOfInstallations": "1698",
                "timestamp": "1646702100"
            },
            {
                "name": "industrial",
                "unit": "kWh",
                "usage": "4490.458765417526",
                "numberOfInstallations": "12498",
                "timestamp": "1646702100"
            }
        ],
        "total": "12828.51349578225"
    },
    "feedIn": {
        "list": [
            {
                "name": "bio",
                "unit": "kWh",
                "usage": "807.5653658083229",
                "numberOfInstallations": "20",
                "installedCapacity": "7853.9",
                "timestamp": "1646702100"
            },
            {
                "name": "solar",
                "unit": "kWh",
                "usage": "0",
                "numberOfInstallations": "14933",
                "installedCapacity": "389081.59000000014",
                "timestamp": "1646702100"
            },
            {
                "name": "water",
                "unit": "kWh",
                "usage": "5911.337670554957",
                "numberOfInstallations": "79",
                "installedCapacity": "31772.7",
                "timestamp": "1646702100"
            },
            {
                "name": "others",
                "unit": "kWh",
                "usage": "270.10517446117456",
                "numberOfInstallations": "111",
                "installedCapacity": "6557.48",
                "timestamp": "1646702100"
            },
            {
                "name": "wind",
                "unit": "kWh",
                "usage": "207.74607637366012",
                "numberOfInstallations": "21",
                "installedCapacity": "32815.1",
                "timestamp": "1646702100"
            }
        ],
        "total": "7196.754287198115"
    },
    "energyMix": "55.77403676112057"
}