{
    "regionCode": "09375",
    "timestamp": {
        "start": "1667545200",
        "end": "1667546100"
    },
    "autarky": "33.26209169226819",
    "secondaryInFeed": "18089.654141701623",
    "consumptions": {
        "list": [
            {
                "name": "domestic",
                "unit": "kWh",
                "usage": "9914.957132256766",
                "numberOfInstallations": "98072",
                "timestamp": "1667545200"
            },
            {
                "name": "public",
                "unit": "kWh",
                "usage": "928.4427753310432",
                "numberOfInstallations": "1723",
                "timestamp": "1667545200"
            },
            {
                "name": "industrial",
                "unit": "kWh",
                "usage": "16262.115683774942",
                "numberOfInstallations": "12526",
                "timestamp": "1667545200"
            }
        ],
        "total": "27105.515591362753"
    },
    "feedIn": {
        "list": [
            {
                "name": "bio",
                "unit": "kWh",
                "usage": "756.4286521042998",
                "numberOfInstallations": "19",
                "installedCapacity": "7633.9",
                "timestamp": "1667545200"
            },
            {
                "name": "solar",
                "unit": "kWh",
                "usage": "2190.638930712279",
                "numberOfInstallations": "15583",
                "installedCapacity": "397762.24500000005",
                "timestamp": "1667545200"
            },
            {
                "name": "water",
                "unit": "kWh",
                "usage": "4275.943460180638",
                "numberOfInstallations": "80",
                "installedCapacity": "31827.7",
                "timestamp": "1667545200"
            },
            {
                "name": "others",
                "unit": "kWh",
                "usage": "200.089654576093",
                "numberOfInstallations": "120",
                "installedCapacity": "6622.915",
                "timestamp": "1667545200"
            },
            {
                "name": "wind",
                "unit": "kWh",
                "usage": "1592.7607520878203",
                "numberOfInstallations": "21",
                "installedCapacity": "32815.1",
                "timestamp": "1667545200"
            }
        ],
        "total": "9015.86144966113"
    },
    "energyMix": "33.11578729479482",
    "dailyCo2Savings": "92537.36274532424"
}