{
    "regionCode": "09375",
    "timestamp": {
        "start": "1636475400",
        "end": "1636476300"
    },
    "autarky": "30.43801499105872",
    "secondaryInFeed": "19825.492640007484",
    "consumptions": {
        "list": [
            {
                "name": "domestic",
                "unit": "kWh",
                "usage": "10212.19155247026",
                "numberOfInstallations": "97543",
                "timestamp": "1636475400"
            },
            {
                "name": "public",
                "unit": "kWh",
                "usage": "1098.3555677563497",
                "numberOfInstallations": "1676",
                "timestamp": "1636475400"
            },
            {
                "name": "industrial",
                "unit": "kWh",
                "usage": "17189.922838270373",
                "numberOfInstallations": "12444",
                "timestamp": "1636475400"
            }
        ],
        "total": "28500.469958496982"
    },
    "feedIn": {
        "list": [
            {
                "name": "bio",
                "unit": "kWh",
                "usage": "908.4613955447127",
                "numberOfInstallations": "20",
                "installedCapacity": "7853.9",
                "timestamp": "1636475400"
            },
            {
                "name": "solar",
                "unit": "kWh",
                "usage": "0",
                "numberOfInstallations": "14791",
                "installedCapacity": "378719.7820000001",
                "timestamp": "1636475400"
            },
            {
                "name": "water",
                "unit": "kWh",
                "usage": "4593.937376220957",
                "numberOfInstallations": "80",
                "installedCapacity": "31886.7",
                "timestamp": "1636475400"
            },
            {
                "name": "others",
                "unit": "kWh",
                "usage": "206.93984567273247",
                "numberOfInstallations": "107",
                "installedCapacity": "6531.38",
                "timestamp": "1636475400"
            },
            {
                "name": "wind",
                "unit": "kWh",
                "usage": "2965.638701051097",
                "numberOfInstallations": "21",
                "installedCapacity": "32815.1",
                "timestamp": "1636475400"
            }
        ],
        "total": "8674.977318489498"
    },
    "energyMix": "30.04728513349883"
}