{
    "regionCode": "09375",
    "timestamp": {
        "start": "1636488000",
        "end": "1636488900"
    },
    "autarky": "32.57736863518125",
    "secondaryInFeed": "16523.69870712687",
    "consumptions": {
        "list": [
            {
                "name": "domestic",
                "unit": "kWh",
                "usage": "11596.635099909292",
                "numberOfInstallations": "97543",
                "timestamp": "1636488000"
            },
            {
                "name": "public",
                "unit": "kWh",
                "usage": "841.0434461331786",
                "numberOfInstallations": "1676",
                "timestamp": "1636488000"
            },
            {
                "name": "industrial",
                "unit": "kWh",
                "usage": "12069.965805181957",
                "numberOfInstallations": "12444",
                "timestamp": "1636488000"
            }
        ],
        "total": "24507.644351224426"
    },
    "feedIn": {
        "list": [
            {
                "name": "bio",
                "unit": "kWh",
                "usage": "900.3246455447124",
                "numberOfInstallations": "20",
                "installedCapacity": "7853.9",
                "timestamp": "1636488000"
            },
            {
                "name": "solar",
                "unit": "kWh",
                "usage": "0",
                "numberOfInstallations": "14791",
                "installedCapacity": "378719.7820000001",
                "timestamp": "1636488000"
            },
            {
                "name": "water",
                "unit": "kWh",
                "usage": "4517.004709554291",
                "numberOfInstallations": "80",
                "installedCapacity": "31886.7",
                "timestamp": "1636488000"
            },
            {
                "name": "others",
                "unit": "kWh",
                "usage": "251.26884567273248",
                "numberOfInstallations": "107",
                "installedCapacity": "6531.38",
                "timestamp": "1636488000"
            },
            {
                "name": "wind",
                "unit": "kWh",
                "usage": "2315.347443325819",
                "numberOfInstallations": "21",
                "installedCapacity": "32815.1",
                "timestamp": "1636488000"
            }
        ],
        "total": "7983.9456440975555"
    },
    "energyMix": "32.12303891363118"
}