{
    "regionCode": "09375",
    "timestamp": {
        "start": "1675681200",
        "end": "1675682100"
    },
    "autarky": "67.21256726612033",
    "secondaryInFeed": "9924.487600900851",
    "consumptions": {
        "list": [
            {
                "name": "domestic",
                "unit": "kWh",
                "usage": "11181.46239588643",
                "numberOfInstallations": "98063",
                "timestamp": "1675681200"
            },
            {
                "name": "public",
                "unit": "kWh",
                "usage": "1071.0732837652972",
                "numberOfInstallations": "1711",
                "timestamp": "1675681200"
            },
            {
                "name": "industrial",
                "unit": "kWh",
                "usage": "18016.646056696147",
                "numberOfInstallations": "12509",
                "timestamp": "1675681200"
            }
        ],
        "total": "30269.181736347877"
    },
    "feedIn": {
        "list": [
            {
                "name": "bio",
                "unit": "kWh",
                "usage": "758.2548619576565",
                "numberOfInstallations": "20",
                "installedCapacity": "5488.9",
                "timestamp": "1675681200"
            },
            {
                "name": "solar",
                "unit": "kWh",
                "usage": "13285.960397650559",
                "numberOfInstallations": "15697",
                "installedCapacity": "286709.5849999999",
                "timestamp": "1675681200"
            },
            {
                "name": "water",
                "unit": "kWh",
                "usage": "3418.532917199862",
                "numberOfInstallations": "77",
                "installedCapacity": "30316.2",
                "timestamp": "1675681200"
            },
            {
                "name": "others",
                "unit": "kWh",
                "usage": "2880.8925220912442",
                "numberOfInstallations": "117",
                "installedCapacity": "30898.18",
                "timestamp": "1675681200"
            },
            {
                "name": "wind",
                "unit": "kWh",
                "usage": "1.0534365477063599",
                "numberOfInstallations": "9",
                "installedCapacity": "815.1",
                "timestamp": "1675681200"
            }
        ],
        "total": "20344.694135447025"
    },
    "energyMix": "58.08333410689433",
    "dailyCo2Savings": "168682.0909127865"
}