{
    "regionCode": "09375",
    "timestamp": {
        "start": "1657632600",
        "end": "1657633500"
    },
    "autarky": "100.0",
    "secondaryInFeed": "0.0",
    "consumptions": {
        "list": [
            {
                "name": "domestic",
                "unit": "kWh",
                "usage": "6005.817432742068",
                "numberOfInstallations": "97818",
                "timestamp": "1657632600"
            },
            {
                "name": "public",
                "unit": "kWh",
                "usage": "665.9901721575654",
                "numberOfInstallations": "1699",
                "timestamp": "1657632600"
            },
            {
                "name": "industrial",
                "unit": "kWh",
                "usage": "12506.741055490213",
                "numberOfInstallations": "12520",
                "timestamp": "1657632600"
            }
        ],
        "total": "19178.548660389846"
    },
    "feedIn": {
        "list": [
            {
                "name": "bio",
                "unit": "kWh",
                "usage": "635.9693941049558",
                "numberOfInstallations": "19",
                "installedCapacity": "7633.9",
                "timestamp": "1657632600"
            },
            {
                "name": "solar",
                "unit": "kWh",
                "usage": "47301.69099442837",
                "numberOfInstallations": "15189",
                "installedCapacity": "392791.92500000016",
                "timestamp": "1657632600"
            },
            {
                "name": "water",
                "unit": "kWh",
                "usage": "3731.357709022576",
                "numberOfInstallations": "81",
                "installedCapacity": "31877.7",
                "timestamp": "1657632600"
            },
            {
                "name": "others",
                "unit": "kWh",
                "usage": "68.06441536342652",
                "numberOfInstallations": "120",
                "installedCapacity": "6617.415",
                "timestamp": "1657632600"
            },
            {
                "name": "wind",
                "unit": "kWh",
                "usage": "1393.258137368673",
                "numberOfInstallations": "21",
                "installedCapacity": "32815.1",
                "timestamp": "1657632600"
            }
        ],
        "total": "53130.340650287995"
    },
    "energyMix": "100.0",
    "dailyCo2Savings": "637959.3368118936"
}