{
    "regionCode": "09375",
    "timestamp": {
        "start": "1653399000",
        "end": "1653399900"
    },
    "autarky": "100.0",
    "secondaryInFeed": "0.0",
    "consumptions": {
        "list": [
            {
                "name": "domestic",
                "unit": "kWh",
                "usage": "6661.65902298333",
                "numberOfInstallations": "97753",
                "timestamp": "1653399000"
            },
            {
                "name": "public",
                "unit": "kWh",
                "usage": "645.7651064029727",
                "numberOfInstallations": "1700",
                "timestamp": "1653399000"
            },
            {
                "name": "industrial",
                "unit": "kWh",
                "usage": "14253.771440391218",
                "numberOfInstallations": "12505",
                "timestamp": "1653399000"
            }
        ],
        "total": "21561.195569777523"
    },
    "feedIn": {
        "list": [
            {
                "name": "bio",
                "unit": "kWh",
                "usage": "603.5670094101183",
                "numberOfInstallations": "19",
                "installedCapacity": "7633.9",
                "timestamp": "1653399000"
            },
            {
                "name": "solar",
                "unit": "kWh",
                "usage": "28449.98074243623",
                "numberOfInstallations": "15076",
                "installedCapacity": "391451.52000000014",
                "timestamp": "1653399000"
            },
            {
                "name": "water",
                "unit": "kWh",
                "usage": "4410.079823372924",
                "numberOfInstallations": "80",
                "installedCapacity": "31859.2",
                "timestamp": "1653399000"
            },
            {
                "name": "others",
                "unit": "kWh",
                "usage": "67.14393102170425",
                "numberOfInstallations": "118",
                "installedCapacity": "6613.015",
                "timestamp": "1653399000"
            },
            {
                "name": "wind",
                "unit": "kWh",
                "usage": "182.8603576295713",
                "numberOfInstallations": "21",
                "installedCapacity": "32815.1",
                "timestamp": "1653399000"
            }
        ],
        "total": "33713.63186387055"
    },
    "energyMix": "100.0"
}